README.rst
setup.cfg
setup.py
py2py/Listener.py
py2py/Sender.py
py2py/__init__.py
py2py.egg-info/PKG-INFO
py2py.egg-info/SOURCES.txt
py2py.egg-info/dependency_links.txt
py2py.egg-info/top_level.txt
py2py/python2/HttpServer.py
py2py/python2/TCPServer.py
py2py/python2/__init__.py
py2py/python3/HttpServer.py
py2py/python3/TCPServer.py
py2py/python3/__init__.py